entitas/__init__.py
entitas-0.0.1.dist-info/LICENSE
entitas-0.0.1.dist-info/METADATA
entitas-0.0.1.dist-info/WHEEL
entitas-0.0.1.dist-info/top_level.txt
entitas-0.0.1.dist-info/RECORD
